bpaste/__init__.py
bpaste/__main__.py
bpaste/exceptions.py
bpaste/languages.py
bpaste/uploader.py
bpaste-1.0.1.dist-info/DESCRIPTION.rst
bpaste-1.0.1.dist-info/METADATA
bpaste-1.0.1.dist-info/RECORD
bpaste-1.0.1.dist-info/WHEEL
bpaste-1.0.1.dist-info/entry_points.txt
bpaste-1.0.1.dist-info/metadata.json
bpaste-1.0.1.dist-info/top_level.txt
