Metadata-Version: 2.0
Name: bpaste
Version: 1.0.1
Summary: Code snippet uploader for bpaste.net
Home-page: https://github.com/cbramy/bpaste
Author: Clement Bramy
Author-email: clement.bramy@gmail.com
License: GPLv3
Keywords: code snippet bpaste syntax
Platform: UNKNOWN
Classifier: Development Status :: 3 - Alpha
Classifier: Intended Audience :: Developers
Classifier: Intended Audience :: End Users/Desktop
Classifier: Intended Audience :: Other Audience
Classifier: Intended Audience :: System Administrators
Classifier: License :: OSI Approved :: GNU General Public License v3 (GPLv3)
Classifier: Programming Language :: Python :: 3
Classifier: Programming Language :: Python :: 3.0
Classifier: Programming Language :: Python :: 3.1
Classifier: Programming Language :: Python :: 3.2
Classifier: Programming Language :: Python :: 3.3
Classifier: Programming Language :: Python :: 3.4
Classifier: Programming Language :: Python :: 3.5
Classifier: Natural Language :: English
Classifier: Operating System :: OS Independent
Classifier: Environment :: Console
Classifier: Topic :: Internet :: WWW/HTTP
Classifier: Topic :: Communications :: File Sharing
Classifier: Topic :: Software Development
Classifier: Topic :: Terminals
Classifier: Topic :: Text Editors
Classifier: Topic :: Text Processing
Classifier: Topic :: Utilities
Requires-Dist: httplib2 (>=0.9.2)
Requires-Dist: pyperclip (>=1.5.26)
